viralquest/__init__.py
viralquest/ai_summary.py
viralquest/cli.py
viralquest/data.py
viralquest/dmndBLASTx.py
viralquest/finalAssets.py
viralquest/finalReport.py
viralquest/hmmsearch.py
viralquest/info.py
viralquest/initialBLAST.py
viralquest/inputFASTA.py
viralquest/main.py
viralquest/mergeJSON.py
viralquest/pfamDomains.py
viralquest/processFASTA.py
viralquest/processORFs.py
viralquest/runBlastn.py
viralquest/bin/blastn.xz
viralquest/bin/cap3
viralquest/bin/diamond.xz
viralquest-2.6.22.dist-info/licenses/LICENSE
viralquest-2.6.22.dist-info/METADATA
viralquest-2.6.22.dist-info/WHEEL
viralquest-2.6.22.dist-info/entry_points.txt
viralquest-2.6.22.dist-info/top_level.txt
viralquest-2.6.22.dist-info/RECORD
