Metadata-Version: 2.4
Name: viralquest
Version: 2.6.22
Summary: A bioinformatics tool for viral genome analysis and characterization.
Author-email: Gabriel Rodrigues <gvpina.rodrigues@gmail.com>
License: MIT
Project-URL: Homepage, https://github.com/gabrielvpina/viralquest
Project-URL: Repository, https://github.com/gabrielvpina/viralquest
Project-URL: Documentation, https://github.com/gabrielvpina/viralquest/blob/main/README.md
Project-URL: Bug Reports, https://github.com/gabrielvpina/viralquest/issues
Keywords: bioinformatics,viral genomics,genome annotation,blast,hmmer
Classifier: Development Status :: 5 - Production/Stable
Classifier: Intended Audience :: Science/Research
Classifier: Topic :: Scientific/Engineering :: Bio-Informatics
Classifier: License :: OSI Approved :: MIT License
Classifier: Programming Language :: Python :: 3.11
Classifier: Programming Language :: Python :: 3.12
Classifier: Operating System :: POSIX :: Linux
Requires-Python: >=3.11
License-File: LICENSE
Requires-Dist: orfipy==0.0.4
Requires-Dist: pandas==2.2.3
Requires-Dist: biopython==1.84
Requires-Dist: more-itertools
Requires-Dist: pyfiglet
Requires-Dist: pyhmmer==0.11.0
Requires-Dist: rich==13.9.4
Requires-Dist: ollama==0.4.7
Requires-Dist: langchain==0.3.7
Requires-Dist: langchain-core==0.3.59
Requires-Dist: langchain-ollama==0.3.2
Requires-Dist: langchain-openai==0.3.17
Requires-Dist: langchain-anthropic==0.3.13
Requires-Dist: langchain-google-genai==2.1.4
Dynamic: license-file
